{
  "info": {
    "key": "b9629_0116"
  },
  "sheets": {
    "מזומנים": {
      "columns": [
        "שם המנפיק/שם נייר ערך",
        "מספר ני\"ע",
        "מספר מנפיק",
        "דירוג",
        "שם מדרג",
        "סוג מטבע",
        "שיעור ריבית",
        "תשואה לפידיון",
        "שווי שוק",
        "שעור מנכסי אפיק ההשקעה",
        "שעור מסך נכסי השקעה"
      ],
      "data": [
        [
          "עו'ש- בנק מזרחי",
          "1111111111- 20- בנק מזרחי",
          20,
          "AAA",
          "מעלות",
          "שקל חדש",
          0,
          0,
          901.47455,
          99.21,
          75.46
        ],
        [
          "דולר- בנק מזרחי",
          "20001- 20- בנק מזרחי",
          20,
          "AAA",
          "מעלות",
          "דולר אמריקאי",
          0,
          0,
          7.21403662,
          0.79,
          0.6
        ]
      ]
    },
    "תעודות התחייבות ממשלתיות": {
      "columns": [
        "שם המנפיק/שם נייר ערך",
        "מספר ני\"ע",
        "זירת מסחר",
        "דירוג",
        "שם מדרג",
        "תאריך רכישה",
        "מח\"מ",
        "סוג מטבע",
        "שיעור ריבית",
        "תשואה לפידיון",
        "ערך נקוב",
        "שער",
        "שווי שוק",
        "שעור מערך נקוב מונפק",
        "שעור מנכסי אפיק ההשקעה",
        "שעור מסך נכסי השקעה"
      ],
      "data": [
        [
          "5903 גליל- האוצר - ממשלתית צמודה",
          9590332,
          "TASE",
          "RF",
          "מעלות",
          "29/03/16",
          4.85,
          "שקל חדש",
          4.0,
          -0.16,
          21340,
          159.79,
          34.099186,
          0,
          30.08,
          2.85
        ],
        [
          "צמוד 0418- האוצר - ממשלתית צמודה",
          1108927,
          "TASE",
          "RF",
          "מעלות",
          "07/03/16",
          1.98,
          "שקל חדש",
          3.5,
          -0.22,
          550,
          128.1,
          0.70455,
          0,
          0.62,
          0.06
        ],
        [
          "צמוד 1019- האוצר - ממשלתית צמודה",
          1114750,
          "TASE",
          "RF",
          "מעלות",
          "23/03/16",
          3.42,
          "שקל חדש",
          3.0,
          -0.4,
          28920,
          122.69,
          35.481948,
          0,
          31.3,
          2.97
        ],
        [
          "ממשלתי 0120- האוצר - ממשלתית שקלית",
          1115773,
          "TASE",
          "RF",
          "מעלות",
          "23/03/16",
          3.58,
          "שקל חדש",
          5.0,
          0.65,
          22250,
          117.26,
          26.09035,
          0,
          23.02,
          2.18
        ],
        [
          "ממשלתי 0122- האוצר - ממשלתית שקלית",
          1123272,
          "TASE",
          "RF",
          "מעלות",
          "21/03/16",
          5.2,
          "שקל חדש",
          5.5,
          1.13,
          13500,
          125.68,
          16.9668,
          0,
          14.97,
          1.42
        ]
      ]
    },
    "תעודות סל": {
      "columns": [
        "שם המנפיק/שם נייר ערך",
        "מספר ני\"ע",
        "זירת מסחר",
        "מספר מנפיק",
        "ענף מסחר",
        "סוג מטבע",
        "ערך נקוב",
        "שער",
        "שווי שוק",
        "שעור מערך נקוב מונפק",
        "שעור מנכסי אפיק ההשקעה",
        "שעור מסך נכסי השקעה"
      ],
      "data": [
        [
          "פסגות סל תל בונד 60 סדרה 3",
          1134550,
          "TASE",
          1108,
          "תעודות סל",
          "שקל חדש",
          505,
          3105.6,
          15.68328,
          0,
          12.49,
          1.31
        ],
        [
          "פסגות תל בונד מאגר",
          1132588,
          "TASE",
          1108,
          "תעודות סל",
          "שקל חדש",
          45,
          3180.4,
          1.43118,
          0,
          1.14,
          0.12
        ],
        [
          "תכלית תל בונד מאגר",
          1132513,
          "TASE",
          1223,
          "תעודות סל",
          "שקל חדש",
          320,
          3180.0,
          10.176,
          0,
          8.1,
          0.85
        ],
        [
          "תכלית תל בונד שקלי סד.2",
          1116524,
          "TASE",
          1223,
          "תעודות סל",
          "שקל חדש",
          3560,
          339.65,
          12.09154,
          0,
          9.63,
          1.01
        ],
        [
          "DAXEX  GY - DAX- BlackRock Fund Advisors",
          "DE0005933931",
          "FWB",
          2235,
          "Other",
          "אירו",
          90,
          8801.0,
          33.94580904,
          0,
          27.03,
          2.84
        ],
        [
          "QQQQ - Nasdaq 100- INVESCO-POWERSHARES",
          "US73935A1043",
          "NASDAQ",
          4643,
          "Other",
          "דולר אמריקאי",
          65,
          10920.0,
          26.731068,
          0,
          21.28,
          2.24
        ],
        [
          "SPY - S&P 500- STATE STREET-SPDRS",
          "US78462F1030",
          "NYSE",
          4640,
          "Other",
          "דולר אמריקאי",
          33,
          20552.0,
          25.54161456,
          0,
          20.34,
          2.14
        ]
      ]
    },
    "קרנות נאמנות": {
      "columns": [
        "שם המנפיק/שם נייר ערך",
        "מספר ני\"ע",
        "זירת מסחר",
        "מספר מנפיק",
        "ענף מסחר",
        "דירוג",
        "שם מדרג",
        "סוג מטבע",
        "ערך נקוב",
        "שער",
        "שווי שוק",
        "שעור מערך נקוב מונפק",
        "שעור מנכסי אפיק ההשקעה",
        "שעור מסך נכסי השקעה"
      ],
      "data": [
        [
          "איביאי סל ת\"א 100 מחקה- אי.בי.אי",
          5113063,
          "TASE",
          175,
          "אחר",
          "A",
          "מעלות",
          "שקל חדש",
          18458,
          130.3,
          24.050774,
          0,
          51.2,
          2.01
        ],
        [
          "ת\"א 25 MTF- מגדל ביטוח הון",
          5109897,
          "TASE",
          1597,
          "אחר",
          0,
          "לא מדורג",
          "שקל חדש",
          15751,
          145.56,
          22.9271556,
          0,
          48.8,
          1.92
        ]
      ]
    },
    "השקעות אחרות ": {
      "columns": [
        "שם המנפיק/שם נייר ערך",
        "מספר הנייר",
        "דירוג",
        "שם המדרג",
        "שעור הריבית",
        "סוג מטבע",
        "תשואה לפדיון",
        "שווי הוגן",
        "שעור מנכסי אפיק ההשקעה",
        "שעור מסך נכסי השקעה"
      ],
      "data": [
        [
          "QQQQ - Nasdaq 100(דיבידנד לקבל)",
          51516,
          0,
          "לא מדורג",
          0,
          "דולר אמריקאי",
          0,
          0.0152,
          36.28,
          0
        ],
        [
          "SPY - S&P 500(דיבידנד לקבל)",
          47373,
          0,
          "לא מדורג",
          0,
          "דולר אמריקאי",
          0,
          0.0267,
          63.72,
          0
        ]
      ]
    }
  }
}