{
  "info": {
    "key": "g1203_0116"
  },
  "sheets": {
    "מזומנים": {
      "columns": [
        "שם המנפיק/שם נייר ערך",
        "מספר ני\"ע",
        "מספר מנפיק",
        "דירוג",
        "שם מדרג",
        "סוג מטבע",
        "שיעור ריבית",
        "תשואה לפדיון",
        "שווי שוק",
        "שעור מנכסי אפיק ההשקעה",
        "שעור מסך נכסי השקעה"
      ],
      "data": [
        [
          "סכומים לקבל תנועות בזמןTמט\"ח",
          "",
          0,
          "AA+",
          "מעלות",
          "שקל חדש",
          0.0,
          0,
          -144.39,
          -0.87,
          -0.05
        ],
        [
          "פועלים סהר-דולר ניו זילנדי",
          "12 - 110005873",
          12,
          "AA+",
          "מעלות",
          "דולר ניו זילנדי",
          0.0,
          0,
          9.7,
          0.06,
          0.0
        ],
        [
          "פועלים סהר-דולר אוסטרלי",
          "12 - 110004702",
          12,
          "AA+",
          "מעלות",
          "דולר אוסטרלי",
          0.0,
          0,
          9.12,
          0.05,
          0.0
        ],
        [
          "פועלים סהר-דולר אמריקאי",
          "12 - 110002805",
          12,
          "AA+",
          "מעלות",
          "דולר אמריקאי",
          0.0,
          0,
          7.67,
          0.05,
          0.0
        ],
        [
          "פועלים סהר-אירו",
          "12 - 110002987",
          12,
          "AA+",
          "מעלות",
          "אירו",
          0.0,
          0,
          78.15,
          0.47,
          0.03
        ],
        [
          "פועלים סהר-שקל חדש",
          "12 - 111111222",
          12,
          "AA+",
          "מעלות",
          "שקל חדש",
          0.02,
          0,
          16624.8,
          100.24,
          5.63
        ]
      ]
    },
    "תעודות התחייבות ממשלתיות": {
      "columns": [
        "שם המנפיק/שם נייר ערך",
        "מספר ני\"ע",
        "זירת מסחר",
        "דירוג",
        "שם מדרג",
        "מח\"מ",
        "סוג מטבע",
        "שיעור ריבית",
        "תשואה לפדיון",
        "ערך נקוב",
        "שער",
        "שווי שוק",
        "שעור מערך נקוב מונפק",
        "שעור מנכסי אפיק ההשקעה",
        "שעור מסך נכסי השקעה"
      ],
      "data": [
        [
          "ממשל צמודה1016",
          1130483,
          "TASE",
          "RF",
          "ללא דירוג",
          0.58,
          "שקל חדש",
          0.1,
          -0.68,
          2695827,
          98.5,
          2655.39,
          0.03,
          1.94,
          0.9
        ],
        [
          "ממשל צמודה0517",
          1125905,
          "TASE",
          "RF",
          "ללא דירוג",
          1.15,
          "שקל חדש",
          1.0,
          -0.31,
          10326668,
          103.82,
          10721.15,
          0.06,
          7.84,
          3.63
        ],
        [
          "ממשל צמודה0536",
          1097708,
          "TASE",
          "RF",
          "ללא דירוג",
          15.2,
          "שקל חדש",
          4.0,
          0.94,
          802959,
          186.16,
          1494.79,
          0.0,
          1.09,
          0.51
        ],
        [
          "גליל5903",
          9590332,
          "TASE",
          "RF",
          "ללא דירוג",
          4.85,
          "שקל חדש",
          4.0,
          -0.1,
          14205556,
          159.79,
          22699.06,
          0.09,
          16.6,
          7.68
        ],
        [
          "גליל5904",
          9590431,
          "TASE",
          "RF",
          "ללא דירוג",
          7.26,
          "שקל חדש",
          4.0,
          0.26,
          4578403,
          161.99,
          7416.55,
          0.04,
          5.42,
          2.51
        ],
        [
          "מ.ק.מ626",
          8160624,
          "TASE",
          "RF",
          "ללא דירוג",
          0.19,
          "שקל חדש",
          0.0,
          0.11,
          3657675,
          99.98,
          3656.94,
          0.03,
          2.67,
          1.24
        ],
        [
          "מ.ק.מ416",
          8160418,
          "TASE",
          "RF",
          "ללא דירוג",
          0.02,
          "שקל חדש",
          0.0,
          0.73,
          2758458,
          99.99,
          2758.18,
          0.02,
          2.02,
          0.93
        ],
        [
          "ממשל משתנה817",
          1106970,
          "TASE",
          "RF",
          "ללא דירוג",
          1.42,
          "שקל חדש",
          0.07,
          0.17,
          25144268,
          99.89,
          25116.61,
          0.16,
          18.36,
          8.5
        ],
        [
          "ממשל שקלית0118",
          1126218,
          "TASE",
          "RF",
          "ללא דירוג",
          1.8,
          "שקל חדש",
          4.0,
          0.22,
          14002421,
          107.59,
          15065.2,
          0.08,
          11.01,
          5.1
        ],
        [
          "ממשל שקלית0217",
          1101575,
          "TASE",
          "RF",
          "ללא דירוג",
          0.91,
          "שקל חדש",
          5.5,
          0.1,
          6401250,
          105.4,
          6746.92,
          0.04,
          4.93,
          2.28
        ],
        [
          "ממשל שקלית0324",
          1130848,
          "TASE",
          "RF",
          "ללא דירוג",
          7.14,
          "שקל חדש",
          3.75,
          1.58,
          2459563,
          116.18,
          2857.52,
          0.02,
          2.09,
          0.97
        ],
        [
          "ממשל שקלית0219",
          1110907,
          "TASE",
          "RF",
          "ללא דירוג",
          2.76,
          "שקל חדש",
          6.0,
          0.43,
          10626549,
          116.6,
          12390.56,
          0.06,
          9.06,
          4.19
        ],
        [
          "ממשל שקלית1026",
          1099456,
          "TASE",
          "RF",
          "ללא דירוג",
          8.35,
          "שקל חדש",
          6.25,
          1.89,
          11112992,
          144.04,
          16007.15,
          0.07,
          11.7,
          5.42
        ],
        [
          "ממשל שקלית0142",
          1125400,
          "TASE",
          "RF",
          "ללא דירוג",
          16.28,
          "שקל חדש",
          5.5,
          2.93,
          4892734,
          146.97,
          7190.85,
          0.03,
          5.26,
          2.43
        ]
      ]
    },
    "אג\"ח קונצרני": {
      "columns": [
        "שם נייר ערך",
        "מספר ני\"ע",
        "זירת מסחר",
        "ספק המידע",
        "מספר מנפיק",
        "ענף מסחר",
        "דירוג",
        "שם מדרג",
        "תאריך רכישה",
        "מח\"מ",
        "סוג מטבע",
        "שיעור ריבית",
        "תשואה לפדיון",
        "ערך נקוב",
        "שער",
        "שווי שוק",
        "שעור מערך נקוב מונפק",
        "שעור מנכסי אפיק ההשקעה",
        "שעור מסך נכסי השקעה",
        "untitled1"
      ],
      "data": [
        [
          "לאומי אגח177",
          6040315,
          "TASE",
          "",
          604,
          "בנקים",
          "AAA",
          "מעלות",
          "",
          4.2,
          "שקל חדש",
          0.59,
          0.91,
          1645939.0,
          98.82,
          1626.52,
          0.03,
          1.65,
          0.55,
          ""
        ],
        [
          "לאומי אגח176",
          6040208,
          "TASE",
          "",
          604,
          "בנקים",
          "AAA",
          "מעלות",
          "",
          0.33,
          "שקל חדש",
          5.05,
          -1.0,
          451210.03,
          135.67,
          612.16,
          0.18,
          0.62,
          0.21,
          ""
        ],
        [
          "מזרחי טפחות הנפק33",
          2310092,
          "TASE",
          "",
          231,
          "בנקים",
          "AAA",
          "מעלות",
          "",
          0.03,
          "שקל חדש",
          2.6,
          1.71,
          1210355.0,
          105.73,
          1279.71,
          0.05,
          1.3,
          0.43,
          ""
        ],
        [
          "פועלים הנפקות אגח31",
          1940527,
          "TASE",
          "",
          194,
          "בנקים",
          "AAA",
          "מעלות",
          "",
          1.34,
          "שקל חדש",
          4.5,
          -0.07,
          735000.0,
          108.37,
          796.52,
          0.15,
          0.81,
          0.27,
          ""
        ],
        [
          "פועלים הנפקות אגח32",
          1940535,
          "TASE",
          "",
          194,
          "בנקים",
          "AAA",
          "מעלות",
          "",
          5.61,
          "שקל חדש",
          5.0,
          0.89,
          2292841.0,
          127.87,
          2931.86,
          0.07,
          2.97,
          0.99,
          ""
        ],
        [
          "'בינלאומי הנפקות אג\"ח ג",
          1093681,
          "TASE",
          "",
          1153,
          "בנקים",
          "AA+",
          "מעלות",
          "",
          1.31,
          "שקל חדש",
          4.2,
          0.04,
          566131.7,
          130.97,
          741.46,
          0.37,
          0.75,
          0.25,
          ""
        ],
        [
          "לאומי התחייבות נדחה יב",
          6040273,
          "TASE",
          "",
          604,
          "בנקים",
          "AA+",
          "מעלות",
          "",
          1.42,
          "שקל חדש",
          2.6,
          0.19,
          1672309.0,
          110.35,
          1845.39,
          0.05,
          1.87,
          0.62,
          ""
        ],
        [
          "מזרחי טפחות30",
          2310068,
          "TASE",
          "",
          231,
          "בנקים",
          "AA+",
          "מעלות",
          "",
          1.12,
          "שקל חדש",
          3.9,
          0.35,
          1619790.0,
          127.07,
          2058.27,
          0.11,
          2.09,
          0.7,
          ""
        ],
        [
          "עזריאלי אגח ב",
          1134436,
          "TASE",
          "",
          1420,
          "נדל\"ן ובינוי",
          "AA+",
          "מעלות",
          "",
          4.88,
          "שקל חדש",
          0.65,
          1.03,
          1022675.4,
          98.19,
          1004.16,
          0.09,
          1.02,
          0.34,
          ""
        ],
        [
          "עזריאלי אגח ב-פדיון לקבל",
          11344360,
          "TASE",
          "",
          1420,
          "נדל\"ן ובינוי",
          "AA+",
          "מעלות",
          "",
          0.0,
          "שקל חדש",
          0.65,
          1.03,
          113630.6,
          100.0,
          113.63,
          0.01,
          0.11,
          0.04,
          ""
        ],
        [
          "פועלים הנפקות הת יד",
          1940501,
          "TASE",
          "",
          194,
          "בנקים",
          "AA+",
          "מעלות",
          "",
          4.73,
          "שקל חדש",
          4.0,
          0.77,
          1666428.0,
          122.47,
          2040.87,
          0.06,
          2.07,
          0.69,
          ""
        ],
        [
          "פועלים הנפקות התח י'",
          1940402,
          "TASE",
          "",
          194,
          "בנקים",
          "AA+",
          "מעלות",
          "",
          2.9,
          "שקל חדש",
          4.1,
          0.62,
          427102.0,
          131.45,
          561.43,
          0.01,
          0.57,
          0.19,
          ""
        ],
        [
          "בזק אגח6",
          2300143,
          "TASE",
          "",
          230,
          "תקשורת ומדיה",
          "AA",
          "מעלות",
          "",
          4.33,
          "שקל חדש",
          3.7,
          0.91,
          1076504.0,
          116.01,
          1248.85,
          0.04,
          1.27,
          0.42,
          ""
        ],
        [
          "בזק אג\"ח5",
          2300069,
          "TASE",
          "",
          230,
          "תקשורת ומדיה",
          "AA",
          "מעלות",
          "",
          0.17,
          "שקל חדש",
          5.3,
          -1.21,
          187537.99,
          128.31,
          240.63,
          0.05,
          0.24,
          0.08,
          ""
        ],
        [
          "בינלאומי הנפ התח כא",
          1126598,
          "TASE",
          "",
          1153,
          "בנקים",
          "AA",
          "מעלות",
          "",
          3.12,
          "שקל חדש",
          2.8,
          0.47,
          1611965.0,
          109.78,
          1769.61,
          0.16,
          1.79,
          0.6,
          ""
        ],
        [
          "בינל הנפקות התח כ",
          1121953,
          "TASE",
          "",
          1153,
          "בנקים",
          "AA",
          "מעלות",
          "",
          2.76,
          "שקל חדש",
          3.1,
          0.44,
          587039.0,
          112.32,
          659.36,
          0.07,
          0.67,
          0.22,
          ""
        ],
        [
          "בינלאומי אג\"ח ה'ז\"פ2017.6.11",
          1105576,
          "TASE",
          "",
          1153,
          "בנקים",
          "AA",
          "מעלות",
          "",
          0.69,
          "שקל חדש",
          3.85,
          0.0,
          1052775.0,
          122.89,
          1293.75,
          0.14,
          1.31,
          0.44,
          ""
        ],
        [
          "הפניקס הון התח א",
          1115104,
          "TASE",
          "",
          1527,
          "ביטוח",
          "AA",
          "מעלות",
          "",
          1.4,
          "שקל חדש",
          4.4,
          0.65,
          736769.0,
          113.13,
          833.51,
          0.41,
          0.85,
          0.28,
          ""
        ],
        [
          "'הראל ביטוח מימון אג\"ח א",
          1099738,
          "TASE",
          "",
          1175,
          "ביטוח",
          "AA",
          "מעלות",
          "",
          3.12,
          "שקל חדש",
          4.65,
          0.59,
          908327.5,
          135.17,
          1227.79,
          0.6,
          1.25,
          0.42,
          ""
        ],
        [
          "נצבא החזקות אגח ה",
          1120468,
          "TASE",
          "",
          1043,
          "נדל\"ן ובינוי",
          "AA",
          "מעלות",
          "",
          3.47,
          "שקל חדש",
          3.0,
          0.84,
          662246.61,
          113.66,
          752.71,
          0.06,
          0.76,
          0.25,
          ""
        ],
        [
          "שטראוס עלית אג\"ח2",
          7460140,
          "TASE",
          "",
          746,
          "מזון",
          "Aa2",
          "מידרוג",
          "",
          1.31,
          "שקל חדש",
          4.1,
          -0.03,
          1533308.19,
          126.16,
          1934.42,
          0.51,
          1.96,
          0.65,
          ""
        ],
        [
          "ריט1אגח ג",
          1120021,
          "TASE",
          "",
          1357,
          "נדל\"ן ובינוי",
          "AA-",
          "מעלות",
          "",
          3.06,
          "שקל חדש",
          3.9,
          0.71,
          480408.51,
          116.44,
          559.39,
          0.11,
          0.57,
          0.19,
          ""
        ],
        [
          "אלוני חץ אג\"ח ו",
          3900206,
          "TASE",
          "",
          390,
          "נדל\"ן ובינוי",
          "AA-",
          "מעלות",
          "",
          1.91,
          "שקל חדש",
          4.25,
          0.79,
          322042.73,
          127.12,
          409.38,
          0.05,
          0.41,
          0.14,
          ""
        ],
        [
          "אמות אג\"ח א'ז\"פ2019.7.5",
          1097385,
          "TASE",
          "",
          1328,
          "נדל\"ן ובינוי",
          "AA-",
          "מעלות",
          "",
          1.7,
          "שקל חדש",
          4.95,
          0.7,
          82420.01,
          129.75,
          106.94,
          0.02,
          0.11,
          0.04,
          ""
        ],
        [
          "בריטיש ישר אגח ג ז\"פ2023.5.30",
          1117423,
          "TASE",
          "",
          1438,
          "נדל\"ן ובינוי",
          "AA-",
          "מעלות",
          "",
          3.39,
          "שקל חדש",
          5.85,
          1.18,
          943328.1,
          126.1,
          1189.54,
          0.05,
          1.21,
          0.4,
          ""
        ],
        [
          "'מנפיקים-חב'להנפק.בנק דסקונט א",
          7480015,
          "TASE",
          "",
          748,
          "בנקים",
          "AA-",
          "מעלות",
          "",
          1.48,
          "שקל חדש",
          5.5,
          0.09,
          362931.62,
          132.78,
          481.9,
          0.23,
          0.49,
          0.16,
          ""
        ],
        [
          "דיסקונט מנפיקים ד.זפ2022.10.30",
          7480049,
          "TASE",
          "",
          748,
          "בנקים",
          "AA-",
          "מעלות",
          "",
          3.4,
          "שקל חדש",
          4.75,
          0.45,
          517668.21,
          135.96,
          703.82,
          0.1,
          0.71,
          0.24,
          ""
        ],
        [
          "'מנפיקים-חב'להנפקות כ.התחיבות ב",
          7480023,
          "TASE",
          "",
          748,
          "בנקים",
          "AA-",
          "מעלות",
          "",
          2.1,
          "שקל חדש",
          5.25,
          0.28,
          207172.0,
          136.48,
          282.75,
          0.04,
          0.29,
          0.1,
          ""
        ],
        [
          "פניקס הון אג ב",
          1120799,
          "TASE",
          "",
          1527,
          "ביטוח",
          "AA-",
          "מעלות",
          "",
          3.33,
          "שקל חדש",
          3.6,
          0.62,
          367353.0,
          115.48,
          424.22,
          0.09,
          0.43,
          0.14,
          ""
        ],
        [
          "מנורה מבטחים אגח א'ז\"פ2022.7.1",
          1103670,
          "TASE",
          "",
          1431,
          "ביטוח",
          "Aa3",
          "מידרוג",
          "",
          3.09,
          "שקל חדש",
          4.05,
          0.57,
          777204.6,
          135.09,
          1049.93,
          0.3,
          1.06,
          0.35,
          ""
        ],
        [
          "מנורה מב אגח א",
          5660048,
          "TASE",
          "",
          566,
          "ביטוח",
          "Aa3",
          "מידרוג",
          "",
          1.73,
          "שקל חדש",
          4.28,
          0.4,
          552237.34,
          130.09,
          718.41,
          0.19,
          0.73,
          0.24,
          ""
        ],
        [
          "ביג אגח ג",
          1106947,
          "TASE",
          "",
          1327,
          "נדל\"ן ובינוי",
          "A+",
          "מעלות",
          "",
          1.94,
          "שקל חדש",
          4.85,
          0.66,
          421752.75,
          129.08,
          544.4,
          0.11,
          0.55,
          0.18,
          ""
        ],
        [
          "ירושלים מ.והנפקות הת ב'ז\"פ2017.3.1",
          1096510,
          "TASE",
          "",
          1248,
          "בנקים",
          "A+",
          "מעלות",
          "",
          0.92,
          "שקל חדש",
          4.8,
          1.14,
          267723.6,
          123.3,
          330.1,
          0.59,
          0.33,
          0.11,
          ""
        ],
        [
          "ישפרו אג\"ח ב'ז\"פ2021.1.4",
          7430069,
          "TASE",
          "",
          743,
          "נדל\"ן ובינוי",
          "A",
          "מעלות",
          "",
          2.61,
          "שקל חדש",
          5.4,
          1.29,
          663246.59,
          132.92,
          881.59,
          0.26,
          0.89,
          0.3,
          ""
        ],
        [
          "נכסים ובנין אגח ד ז\"פ2025.12.31",
          6990154,
          "TASE",
          "",
          699,
          "נדל\"ן ובינוי",
          "A",
          "מעלות",
          "",
          6.18,
          "שקל חדש",
          4.95,
          3.02,
          1612375.0,
          135.0,
          2176.71,
          0.1,
          2.21,
          0.74,
          ""
        ],
        [
          "שופרסל אגח ד",
          7770191,
          "TASE",
          "",
          777,
          "מסחר",
          "A",
          "מעלות",
          "",
          6.2,
          "שקל חדש",
          2.99,
          2.68,
          403097.36,
          103.3,
          416.4,
          0.1,
          0.42,
          0.14,
          ""
        ],
        [
          "'שופרסל אג\"ח ב",
          7770142,
          "TASE",
          "",
          777,
          "מסחר",
          "A",
          "מעלות",
          "",
          1.96,
          "שקל חדש",
          5.2,
          1.2,
          353041.2,
          131.4,
          463.9,
          0.03,
          0.47,
          0.16,
          ""
        ],
        [
          "שלמה החז אגח טז-פדיון לקבל",
          14102810,
          "TASE",
          "",
          141,
          "שרותים",
          "A",
          "מעלות",
          "",
          0.0,
          "שקל חדש",
          2.15,
          2.02,
          27972.0,
          100.0,
          27.97,
          0.01,
          0.03,
          0.01,
          ""
        ],
        [
          "שלמה החז אגח טז",
          1410281,
          "TASE",
          "",
          141,
          "שרותים",
          "A",
          "מעלות",
          "",
          3.49,
          "שקל חדש",
          2.15,
          2.02,
          783216.0,
          100.45,
          786.74,
          0.37,
          0.8,
          0.27,
          ""
        ],
        [
          "אלבר אגח יג",
          1127588,
          "TASE",
          "",
          1382,
          "שרותים",
          "A3",
          "מידרוג",
          "",
          1.48,
          "שקל חדש",
          4.2,
          1.75,
          779344.5,
          104.6,
          815.19,
          0.14,
          0.83,
          0.28,
          ""
        ],
        [
          "דה לסר אגח ב",
          1118587,
          "TASE",
          "",
          1513,
          "נדל\"ן ובינוי",
          "A-",
          "מעלות",
          "",
          1.83,
          "שקל חדש",
          6.4,
          3.22,
          175950.0,
          116.0,
          204.1,
          0.15,
          0.21,
          0.07,
          ""
        ],
        [
          "בזן אגח א",
          2590255,
          "TASE",
          "",
          259,
          "כימיה גומי ופלסטיק",
          "BBB+",
          "מעלות",
          "",
          2.14,
          "שקל חדש",
          4.8,
          2.53,
          214893.0,
          122.98,
          264.27,
          0.02,
          0.27,
          0.09,
          ""
        ],
        [
          "אלביט הד אגח ח",
          1131267,
          "TASE",
          "",
          1039,
          "השקעה ואחזקות",
          "ללא דירוג",
          "ללא דירוג",
          "",
          2.02,
          "שקל חדש",
          6.0,
          11.88,
          802831.0,
          91.12,
          731.54,
          0.21,
          0.74,
          0.25,
          ""
        ],
        [
          "דלק אנרגיה אגחה",
          5650114,
          "TASE",
          "",
          565,
          "חיפושי נפט וגז",
          "ללא דירוג",
          "ללא דירוג",
          "",
          1.9,
          "שקל חדש",
          5.15,
          1.37,
          347497.23,
          115.24,
          400.46,
          0.08,
          0.41,
          0.14,
          ""
        ],
        [
          "פועלים הנ אג29",
          1940485,
          "TASE",
          "",
          194,
          "בנקים",
          "AAA",
          "מעלות",
          "",
          2.04,
          "שקל חדש",
          5.9,
          0.89,
          1167843.0,
          112.69,
          1316.04,
          0.07,
          1.33,
          0.44,
          ""
        ],
        [
          "אלביט מערכות אגח א",
          1119635,
          "TASE",
          "",
          1040,
          "ביטחוניות",
          "Aa1",
          "מידרוג",
          "",
          2.17,
          "שקל חדש",
          4.84,
          0.85,
          1998549.83,
          110.05,
          2199.4,
          0.19,
          2.23,
          0.74,
          ""
        ],
        [
          "לאומי התחייבות נדחה יג",
          6040281,
          "TASE",
          "",
          604,
          "בנקים",
          "AA+",
          "מעלות",
          "",
          1.39,
          "שקל חדש",
          5.4,
          0.78,
          2257236.0,
          109.6,
          2473.93,
          0.1,
          2.51,
          0.84,
          ""
        ],
        [
          "פועלים הנפקות יא'ז\"פ2021.3.28",
          1940410,
          "TASE",
          "",
          194,
          "בנקים",
          "AA+",
          "מעלות",
          "",
          2.86,
          "שקל חדש",
          6.1,
          1.19,
          2269093.0,
          114.34,
          2594.48,
          0.13,
          2.63,
          0.88,
          ""
        ],
        [
          "דיסקונט התחייבות יא",
          6910137,
          "TASE",
          "",
          691,
          "בנקים",
          "AA-",
          "מעלות",
          "",
          4.14,
          "שקל חדש",
          6.4,
          1.5,
          1709964.0,
          124.08,
          2121.72,
          0.52,
          2.15,
          0.72,
          ""
        ],
        [
          "דיסקונט מנ הת ט",
          7480106,
          "TASE",
          "",
          748,
          "בנקים",
          "AA-",
          "מעלות",
          "",
          1.4,
          "שקל חדש",
          2.08,
          0.9,
          1179463.0,
          101.88,
          1201.64,
          0.15,
          1.22,
          0.41,
          ""
        ],
        [
          "'דיסקונט מנפיקים הת.ה",
          7480031,
          "TASE",
          "",
          748,
          "בנקים",
          "AA-",
          "מעלות",
          "",
          1.89,
          "שקל חדש",
          6.1,
          0.84,
          332011.8,
          110.44,
          366.67,
          0.07,
          0.37,
          0.12,
          ""
        ],
        [
          "פניקס הון אג ג",
          1120807,
          "TASE",
          "",
          1527,
          "ביטוח",
          "AA-",
          "מעלות",
          "",
          1.46,
          "שקל חדש",
          6.0,
          0.9,
          592738.0,
          107.59,
          637.73,
          0.38,
          0.65,
          0.22,
          ""
        ],
        [
          "כללביט אגח ו",
          1120138,
          "TASE",
          "",
          1324,
          "ביטוח",
          "AA-",
          "מעלות",
          "",
          1.29,
          "שקל חדש",
          5.7,
          0.0,
          2291113.0,
          108.55,
          2487.0,
          0.31,
          2.52,
          0.84,
          ""
        ],
        [
          "קיי.בי.אס אגח א",
          1137918,
          "TASE",
          "",
          1662,
          "נדל\"ן ובינוי",
          "AA-",
          "מעלות",
          "",
          4.45,
          "שקל חדש",
          4.25,
          4.13,
          1031262.0,
          100.99,
          1041.47,
          0.11,
          1.06,
          0.35,
          ""
        ],
        [
          "קרסו אגח א",
          1136464,
          "TASE",
          "",
          1585,
          "מסחר",
          "Aa3",
          "מידרוג",
          "",
          5.0,
          "שקל חדש",
          2.75,
          2.25,
          1336440.01,
          102.8,
          1373.86,
          0.51,
          1.39,
          0.46,
          ""
        ],
        [
          "דלק קבוצה אגח טו",
          1115070,
          "TASE",
          "",
          1095,
          "השקעה ואחזקות",
          "A1",
          "מידרוג",
          "",
          1.0,
          "שקל חדש",
          8.5,
          1.02,
          422120.02,
          111.61,
          471.13,
          0.08,
          0.48,
          0.16,
          ""
        ],
        [
          "דלק קבוצה אגח יד",
          1115062,
          "TASE",
          "",
          1095,
          "השקעה ואחזקות",
          "A1",
          "מידרוג",
          "",
          2.09,
          "שקל חדש",
          8.5,
          1.63,
          1282630.0,
          117.22,
          1503.5,
          0.31,
          1.52,
          0.51,
          ""
        ],
        [
          "לייטסטון אגח א",
          1133891,
          "TASE",
          "",
          1630,
          "נדל\"ן ובינוי",
          "A+",
          "מעלות",
          "",
          4.43,
          "שקל חדש",
          6.05,
          4.23,
          944420.0,
          110.48,
          1043.39,
          0.16,
          1.06,
          0.35,
          ""
        ],
        [
          "פתאל אגח א",
          1137512,
          "TASE",
          "",
          1661,
          "נדל\"ן ובינוי",
          "A1",
          "מידרוג",
          "",
          4.85,
          "שקל חדש",
          3.5,
          3.45,
          732955.0,
          100.69,
          738.01,
          0.3,
          0.75,
          0.25,
          ""
        ],
        [
          "רילייטד אגח א",
          1134923,
          "TASE",
          "",
          1638,
          "נדל\"ן ובינוי",
          "A+",
          "מעלות",
          "",
          3.88,
          "שקל חדש",
          5.1,
          4.2,
          967994.0,
          103.65,
          1003.33,
          0.11,
          1.02,
          0.34,
          ""
        ],
        [
          "דלק קב אגח לא",
          1134790,
          "TASE",
          "",
          1095,
          "השקעה ואחזקות",
          "A",
          "מעלות",
          "",
          6.13,
          "שקל חדש",
          4.3,
          4.42,
          2153160.0,
          100.05,
          2154.24,
          0.09,
          2.19,
          0.73,
          ""
        ],
        [
          "סטרוברי אגח א",
          1136951,
          "TASE",
          "",
          1654,
          "נדל\"ן ובינוי",
          "A",
          "מעלות",
          "",
          3.71,
          "שקל חדש",
          6.4,
          5.53,
          1001879.0,
          105.69,
          1058.89,
          0.38,
          1.07,
          0.36,
          ""
        ],
        [
          "ספנסר אגח א",
          1133800,
          "TASE",
          "",
          1628,
          "נדל\"ן ובינוי",
          "A",
          "מעלות",
          "",
          3.99,
          "שקל חדש",
          6.9,
          4.39,
          1012982.0,
          112.81,
          1142.74,
          0.17,
          1.16,
          0.39,
          ""
        ],
        [
          "קופרליין אגח א",
          1136589,
          "TASE",
          "",
          1648,
          "נדל\"ן ובינוי",
          "A",
          "מעלות",
          "",
          2.84,
          "שקל חדש",
          6.0,
          4.48,
          987400.0,
          107.32,
          1059.68,
          0.29,
          1.07,
          0.36,
          ""
        ],
        [
          "אלבר אגח יד",
          1132562,
          "TASE",
          "",
          1382,
          "שרותים",
          "A3",
          "מידרוג",
          "",
          2.73,
          "שקל חדש",
          3.3,
          2.43,
          1172548.54,
          102.86,
          1206.08,
          0.23,
          1.22,
          0.41,
          ""
        ],
        [
          "דה לסר אגח ה",
          1135664,
          "TASE",
          "",
          1513,
          "נדל\"ן ובינוי",
          "A-",
          "מעלות",
          "",
          5.76,
          "שקל חדש",
          6.9,
          7.33,
          1024153.0,
          100.86,
          1032.96,
          0.28,
          1.05,
          0.35,
          ""
        ],
        [
          "קליין אגח א",
          1136977,
          "TASE",
          "",
          1658,
          "נדל\"ן ובינוי",
          "A3",
          "מידרוג",
          "",
          3.58,
          "שקל חדש",
          6.4,
          5.8,
          995000.0,
          102.95,
          1024.35,
          0.42,
          1.04,
          0.35,
          ""
        ],
        [
          "גינדי אגח ד",
          1136514,
          "TASE",
          "",
          1308,
          "נדל\"ן ובינוי",
          "ללא דירוג",
          "ללא דירוג",
          "",
          2.09,
          "שקל חדש",
          6.75,
          5.53,
          690000.0,
          104.4,
          720.36,
          0.63,
          0.73,
          0.24,
          ""
        ],
        [
          "ISRAEL ELECTRIC 8.1 15/12/96",
          "USM60170AC79",
          "אחר",
          "בלומברג",
          99189,
          "Utilities",
          "BBB-",
          "S&P",
          "",
          12.51,
          "דולר אמריקאי",
          8.1,
          8.1,
          405000.0,
          114.87,
          1752.11,
          0.32,
          1.78,
          0.59,
          60088804
        ],
        [
          "FRIPRO 12 5/21",
          "XS0430178961",
          "LSE",
          "בלומברג",
          97181,
          "Insurance",
          "A",
          "S&P",
          "",
          3.95,
          "לירה שטרלינג",
          12.0,
          4.62,
          53000.0,
          143.3,
          412.16,
          0.03,
          0.42,
          0.14,
          60344215
        ],
        [
          "AMXLMM 7 1/8 12/09/24",
          "XS1075314911",
          "אחר",
          "בלומברג",
          98335,
          "Telecommunication Services",
          "A-",
          "S&P",
          "",
          6.51,
          "פזו מקסיקני",
          7.12,
          7.52,
          2300000.0,
          99.67,
          503.85,
          0.02,
          0.51,
          0.17,
          60360385
        ],
        [
          "DAIL 7 1/4 12/29/49",
          "USJ09748AB01",
          "SGX",
          "בלומברג",
          97526,
          "Insurance",
          "A-",
          "S&P",
          "",
          4.52,
          "דולר אמריקאי",
          7.25,
          4.68,
          155000.0,
          119.75,
          699.0,
          0.01,
          0.71,
          0.24,
          60271251
        ],
        [
          "DORIC 5 1/8 11/30/22",
          "US258258AA01",
          "אחר",
          "בלומברג",
          91750,
          "Capital Goods",
          "A3",
          "MOODIES",
          "",
          5.63,
          "דולר אמריקאי",
          5.12,
          4.9,
          140000.0,
          102.97,
          542.89,
          0.03,
          0.55,
          0.18,
          60398815
        ],
        [
          "NGGLN 0 11/04/21",
          "XS0034394709",
          "LSE",
          "בלומברג",
          97417,
          "Utilities",
          "A-",
          "S&P",
          "",
          6.31,
          "דולר אמריקאי",
          0.0,
          2.95,
          220000.0,
          85.01,
          704.35,
          0.01,
          0.71,
          0.24,
          60119849
        ],
        [
          "ASBBNK 6.65 06/15/24",
          "NZABBDG001C4",
          "אחר",
          "בלומברג",
          97467,
          "Banks",
          "BBB+",
          "S&P",
          "",
          2.9,
          "דולר ניו זילנדי",
          6.65,
          4.66,
          223000.0,
          105.95,
          618.18,
          0.06,
          0.63,
          0.21,
          60357241
        ],
        [
          "T 3.8 03/15/22",
          "US00206RDB50",
          "אחר",
          "בלומברג",
          99144,
          "Telecommunication Services",
          "BBB+",
          "S&P",
          "",
          5.38,
          "דולר אמריקאי",
          3.8,
          2.77,
          130000.0,
          105.79,
          517.91,
          0.01,
          0.52,
          0.17,
          60403367
        ],
        [
          "CP 6 1/8 09/15/15",
          "US13645RAX26",
          "אחר",
          "בלומברג",
          98899,
          "Transportation",
          "BBB+",
          "S&P",
          "",
          17.75,
          "דולר אמריקאי",
          6.12,
          5.75,
          115000.0,
          106.77,
          462.42,
          0.01,
          0.47,
          0.16,
          60400868
        ],
        [
          "DLGLN 9 1/4 04/27/42",
          "XS0773947618",
          "LSE",
          "בלומברג",
          97463,
          "Insurance",
          "BBB+",
          "S&P",
          "",
          4.74,
          "לירה שטרלינג",
          9.25,
          7.17,
          70000.0,
          124.24,
          471.97,
          0.01,
          0.48,
          0.16,
          60356730
        ],
        [
          "TELVIS 7 1/4 05/14/43",
          "XS0931063779",
          "אחר",
          "בלומברג",
          97893,
          "Media",
          "BBB+",
          "S&P",
          "",
          10.6,
          "פזו מקסיקני",
          7.25,
          8.96,
          2000000.0,
          85.36,
          375.26,
          0.03,
          0.38,
          0.13,
          60384559
        ],
        [
          "RSALN 9 3/8 05/20/39",
          "XS0429467961",
          "LSE",
          "בלומברג",
          94768,
          "Insurance",
          "BBB+",
          "S&P",
          "",
          2.68,
          "לירה שטרלינג",
          9.37,
          7.77,
          55000.0,
          124.6,
          371.89,
          0.01,
          0.38,
          0.13,
          60357258
        ],
        [
          "AIOAU 5 1/4 05/19/25",
          "AU3CB0229680",
          "DAX",
          "בלומברג",
          98850,
          "Transportation",
          "BBB",
          "S&P",
          "",
          7.21,
          "דולר אוסטרלי",
          5.25,
          5.33,
          70000.0,
          101.5,
          205.8,
          0.02,
          0.21,
          0.07,
          60386869
        ],
        [
          "BACAU 6 10/21/20",
          "AU3CB0214823",
          "אחר",
          "בלומברג",
          97360,
          "Transportation",
          "BBB",
          "S&P",
          "",
          3.97,
          "דולר אוסטרלי",
          6.0,
          3.94,
          90000.0,
          111.34,
          290.24,
          0.03,
          0.29,
          0.1,
          60340569
        ],
        [
          "CSC 4.45 09/22",
          "US205363AN41",
          "אחר",
          "בלומברג",
          97612,
          "Software & Services",
          "BBB",
          "S&P",
          "",
          5.67,
          "דולר אמריקאי",
          4.45,
          3.99,
          110000.0,
          102.77,
          425.75,
          0.02,
          0.43,
          0.14,
          60379658
        ],
        [
          "DOWAU 4 1/2 03/11/22",
          "AU3CB0228070",
          "אחר",
          "בלומברג",
          97471,
          "Commercial & Professional Services",
          "BBB",
          "פנימי",
          "",
          5.25,
          "דולר אוסטרלי",
          4.5,
          4.97,
          140000.0,
          98.06,
          397.63,
          0.06,
          0.4,
          0.13,
          60386950
        ],
        [
          "LIMAMT 5 7/8 07/05/34",
          "USG54897AA45",
          "אחר",
          "בלומברג",
          96102,
          "Transportation",
          "BBB",
          "S&P",
          "",
          11.29,
          "דולר אמריקאי",
          5.87,
          5.91,
          110000.0,
          100.97,
          418.3,
          0.01,
          0.42,
          0.14,
          60395316
        ],
        [
          "PSON 3.25 05/23",
          "US70501VAA61",
          "אחר",
          "בלומברג",
          91174,
          "Media",
          "BBB",
          "S&P",
          "",
          6.28,
          "דולר אמריקאי",
          3.25,
          4.06,
          160000.0,
          96.34,
          580.54,
          0.03,
          0.59,
          0.2,
          60329331
        ],
        [
          "PSON 3 3/4 05/08/22",
          "US705011AA25",
          "אחר",
          "בלומברג",
          91174,
          "Media",
          "BBB",
          "S&P",
          "",
          5.42,
          "דולר אמריקאי",
          3.75,
          3.72,
          70000.0,
          101.66,
          267.99,
          0.01,
          0.27,
          0.09,
          60402591
        ],
        [
          "TRPCN 6.35 05/15/67",
          "US89352HAC34",
          "אחר",
          "בלומברג",
          99333,
          "Energy",
          "BBB",
          "S&P",
          "",
          1.05,
          "דולר אמריקאי",
          6.35,
          4.53,
          120000.0,
          72.79,
          328.94,
          0.01,
          0.33,
          0.11,
          60276151
        ],
        [
          "WU 6.2 06/21/40",
          "US959802AM19",
          "NYSE",
          "בלומברג",
          98024,
          "Software & Services",
          "BBB",
          "S&P",
          "",
          12.55,
          "דולר אמריקאי",
          6.2,
          6.29,
          260000.0,
          100.57,
          984.71,
          0.1,
          1.0,
          0.33,
          60382496
        ],
        [
          "BCP6.125 4/27",
          "USP09646AE32",
          "DAX",
          "בלומברג",
          92773,
          "Banks",
          "BBB-",
          "S&P",
          "",
          5.05,
          "דולר אמריקאי",
          6.12,
          5.9,
          120000.0,
          109.29,
          493.92,
          0.02,
          0.5,
          0.17,
          60299526
        ],
        [
          "BACR 10 1//1",
          "XS0429325748",
          "LSE",
          "בלומברג",
          99305,
          "Banks",
          "BBB-",
          "S&P",
          "",
          4.07,
          "לירה שטרלינג",
          10.0,
          4.34,
          70000.0,
          134.11,
          509.47,
          0.0,
          0.52,
          0.17,
          60289873
        ],
        [
          "CBG 5 03/15/23",
          "US12505BAA89",
          "אחר",
          "בלומברג",
          98910,
          "Real Estate",
          "Baa3",
          "MOODIES",
          "",
          5.95,
          "דולר אמריקאי",
          5.0,
          4.56,
          135000.0,
          102.79,
          522.59,
          0.02,
          0.53,
          0.18,
          60401502
        ],
        [
          "CENSUD 5.15 02/12/25",
          "USP2205JAK62",
          "אחר",
          "בלומברג",
          97501,
          "Food & Staples Retailing",
          "Baa3",
          "MOODIES",
          "",
          7.17,
          "דולר אמריקאי",
          5.15,
          5.0,
          225000.0,
          101.72,
          861.9,
          0.03,
          0.87,
          0.29,
          60379518
        ],
        [
          "CENSUD 6 5/8 02/12/45",
          "USP2205JAL46",
          "אחר",
          "בלומברג",
          97501,
          "Food & Staples Retailing",
          "Baa3",
          "MOODIES",
          "",
          12.64,
          "דולר אמריקאי",
          6.62,
          7.12,
          85000.0,
          94.85,
          303.61,
          0.02,
          0.31,
          0.1,
          60383387
        ],
        [
          "COLPIP 5.8 6/45",
          "USU2097KAD47",
          "DAX",
          "בלומברג",
          98857,
          "Utilities",
          "BBB-",
          "S&P",
          "",
          14.14,
          "דולר אמריקאי",
          5.8,
          5.77,
          110000.0,
          102.39,
          424.15,
          0.02,
          0.43,
          0.14,
          60387701
        ],
        [
          "FFHCN 5.8 05/15/21",
          "USC33459AA30",
          "אחר",
          "בלומברג",
          99863,
          "Insurance",
          "BBB-",
          "S&P",
          "",
          4.42,
          "דולר אמריקאי",
          5.8,
          4.57,
          55000.0,
          107.72,
          223.12,
          0.01,
          0.23,
          0.08,
          60334133
        ],
        [
          "FFHCN 5.8 5//1",
          "US303901AS14",
          "אחר",
          "בלומברג",
          99863,
          "Insurance",
          "BBB-",
          "S&P",
          "",
          4.42,
          "דולר אמריקאי",
          5.8,
          4.58,
          180000.0,
          107.67,
          729.88,
          0.04,
          0.74,
          0.25,
          60314234
        ],
        [
          "FFHCN 8.3 04/15/26",
          "US303901AB88",
          "אחר",
          "בלומברג",
          99863,
          "Insurance",
          "BBB-",
          "S&P",
          "",
          7.07,
          "דולר אמריקאי",
          8.3,
          5.55,
          115000.0,
          124.76,
          540.31,
          0.09,
          0.55,
          0.18,
          60380102
        ],
        [
          "HPT 4 1/4 02/15/21",
          "US44106MAU62",
          "אחר",
          "בלומברג",
          98900,
          "Real Estate",
          "BBB-",
          "S&P",
          "",
          4.42,
          "דולר אמריקאי",
          4.25,
          3.27,
          150000.0,
          105.04,
          593.39,
          0.04,
          0.6,
          0.2,
          60400876
        ],
        [
          "KMI 6 1/2 04/01/20",
          "US28370TAA79",
          "אחר",
          "בלומברג",
          98875,
          "Energy",
          "BBB-",
          "S&P",
          "",
          3.59,
          "דולר אמריקאי",
          6.5,
          4.54,
          105000.0,
          110.33,
          436.29,
          0.02,
          0.44,
          0.15,
          60398823
        ],
        [
          "MSI 3 3/4 05/15/22",
          "US620076BB42",
          "NYSE",
          "בלומברג",
          99308,
          "Technology Hardware & Equipment",
          "BBB-",
          "S&P",
          "",
          5.43,
          "דולר אמריקאי",
          3.75,
          4.12,
          160000.0,
          99.43,
          599.14,
          0.02,
          0.61,
          0.2,
          60373719
        ],
        [
          "QBEAU 6.75 44",
          "XS1144495808",
          "SGX",
          "בלומברג",
          98276,
          "Insurance",
          "BBB-",
          "S&P",
          "",
          6.6,
          "דולר אמריקאי",
          6.75,
          6.0,
          240000.0,
          107.12,
          968.21,
          0.03,
          0.98,
          0.33,
          60374345
        ],
        [
          "ACIAIR 6 7/8 11/29/32",
          "USE0351QAA07",
          "אחר",
          "בלומברג",
          97908,
          "Transportation",
          "BB+",
          "S&P",
          "",
          9.1,
          "דולר אמריקאי",
          6.87,
          9.2,
          160000.0,
          82.67,
          498.14,
          0.08,
          0.5,
          0.17,
          60386166
        ],
        [
          "CHTRIG 4.46 22",
          "US161175AL87",
          "אחר",
          "בלומברג",
          97910,
          "Media",
          "Ba1",
          "MOODIES",
          "",
          5.53,
          "דולר אמריקאי",
          4.46,
          3.62,
          170000.0,
          105.53,
          675.63,
          0.01,
          0.68,
          0.23,
          60392495
        ],
        [
          "BAC8.05 06/27",
          "US22237AAB26",
          "NYSE",
          "בלומברג",
          99491,
          "Banks",
          "BB+",
          "S&P",
          "",
          7.83,
          "דולר אמריקאי",
          8.05,
          5.16,
          90000.0,
          126.68,
          429.38,
          0.04,
          0.44,
          0.14,
          60358538
        ],
        [
          "MRPNZ 6.9 7/44",
          "NZMRPDG001C6",
          "אחר",
          "בלומברג",
          97792,
          "Utilities",
          "BB+",
          "S&P",
          "",
          2.97,
          "דולר ניו זילנדי",
          6.9,
          6.35,
          120000.0,
          107.54,
          337.65,
          0.04,
          0.34,
          0.11,
          60363926
        ],
        [
          "TITIM5.303 5/24",
          "US87927YAA01",
          "ISE",
          "בלומברג",
          98161,
          "Telecommunication Services",
          "BB+",
          "S&P",
          "",
          6.63,
          "דולר אמריקאי",
          5.3,
          4.81,
          265000.0,
          105.02,
          1048.07,
          0.02,
          1.06,
          0.35,
          60359528
        ],
        [
          "BCP 9 3/4 11/06/69",
          "USP09646AB92",
          "אחר",
          "בלומברג",
          97806,
          "Banks",
          "BB",
          "S&P",
          "",
          3.04,
          "דולר אמריקאי",
          9.75,
          7.79,
          95000.0,
          120.28,
          430.33,
          0.04,
          0.44,
          0.15,
          60380094
        ],
        [
          "BACR 14 11/49",
          "XS0397801357",
          "LSE",
          "בלומברג",
          99305,
          "Banks",
          "BB",
          "S&P",
          "",
          2.61,
          "לירה שטרלינג",
          14.0,
          11.29,
          35000.0,
          137.7,
          261.56,
          0.0,
          0.26,
          0.09,
          60213220
        ],
        [
          "CTL 7.995 06/01/36",
          "US29078EAA38",
          "NYSE",
          "בלומברג",
          97895,
          "Telecommunication Services",
          "BB",
          "S&P",
          "",
          9.9,
          "דולר אמריקאי",
          7.99,
          8.31,
          150000.0,
          99.6,
          562.66,
          0.01,
          0.57,
          0.19,
          60384690
        ],
        [
          "JBSSBZ 5 3/4 06/15/25",
          "US466112AR07",
          "אחר",
          "בלומברג",
          98581,
          "Food Beverage & Tobacco",
          "Ba2",
          "MOODIES",
          "",
          6.98,
          "דולר אמריקאי",
          5.75,
          7.55,
          110000.0,
          89.91,
          372.48,
          0.01,
          0.38,
          0.13,
          60387792
        ],
        [
          "ROCKIE6.85 7/18",
          "USU75111AC56",
          "אחר",
          "בלומברג",
          98769,
          "Energy",
          "Ba2",
          "MOODIES",
          "",
          2.11,
          "דולר אמריקאי",
          6.85,
          6.84,
          85000.0,
          101.43,
          324.68,
          0.01,
          0.33,
          0.11,
          60605953
        ],
        [
          "RBS 5.125 05/24",
          "US780099CH81",
          "אחר",
          "בלומברג",
          98508,
          "Banks",
          "BB",
          "S&P",
          "",
          6.61,
          "דולר אמריקאי",
          5.12,
          5.67,
          220000.0,
          98.25,
          814.03,
          0.01,
          0.83,
          0.28,
          60359106
        ],
        [
          "SMIPET 7.75 20",
          "USP84523AA03",
          "אחר",
          "בלומברג",
          97528,
          "Materials",
          "Ba2",
          "MOODIES",
          "",
          3.83,
          "דולר אמריקאי",
          7.75,
          7.51,
          120000.0,
          104.02,
          470.08,
          0.06,
          0.48,
          0.16,
          60342458
        ],
        [
          "BEEBZ8.75 12/49",
          "USL6401PAD52",
          "SGX",
          "בלומברג",
          97525,
          "Food Beverage & Tobacco",
          "BB-",
          "S&P",
          "",
          2.65,
          "דולר אמריקאי",
          8.75,
          8.95,
          120000.0,
          96.03,
          433.96,
          0.04,
          0.44,
          0.15,
          60355096
        ],
        [
          "BEEFBZ 10.875 1",
          "USG6147PAA69",
          "SGX",
          "בלומברג",
          97525,
          "Food Beverage & Tobacco",
          "BB-",
          "S&P",
          "",
          2.97,
          "דולר אמריקאי",
          10.87,
          10.02,
          35000.0,
          106.58,
          140.48,
          0.01,
          0.14,
          0.05,
          60367711
        ],
        [
          "TMUS 6.625 20",
          "US591709AL49",
          "אחר",
          "בלומברג",
          97422,
          "Real Estate",
          "Ba3",
          "MOODIES",
          "",
          3.96,
          "דולר אמריקאי",
          6.62,
          5.79,
          105000.0,
          105.82,
          418.43,
          0.01,
          0.42,
          0.14,
          60393220
        ],
        [
          "AAL 6 1/8 06/01/18",
          "US91731VAA44",
          "אחר",
          "בלומברג",
          97413,
          "Transportation",
          "B+",
          "S&P",
          "",
          2.01,
          "דולר אמריקאי",
          6.12,
          3.89,
          140000.0,
          106.6,
          562.06,
          0.03,
          0.57,
          0.19,
          60398245
        ],
        [
          "DAN 5 3/8 09/15/21",
          "US235825AC01",
          "NYSE",
          "בלומברג",
          97981,
          "Automobiles and Components",
          "B1",
          "MOODIES",
          "",
          4.78,
          "דולר אמריקאי",
          5.37,
          5.28,
          105000.0,
          100.68,
          398.11,
          0.02,
          0.4,
          0.13,
          60392958
        ],
        [
          "MRFGBZ 9.625 16",
          "USG5814RAA61",
          "אחר",
          "בלומברג",
          97717,
          "Food Beverage & Tobacco",
          "B2",
          "MOODIES",
          "",
          0.59,
          "דולר אמריקאי",
          9.62,
          5.8,
          85000.0,
          105.83,
          338.78,
          0.02,
          0.34,
          0.11,
          60324548
        ]
      ]
    },
    "תעודות סל": {
      "columns": [
        "שם נייר ערך",
        "מספר ני\"ע",
        "זירת מסחר",
        "מספר מנפיק",
        "ענף מסחר",
        "סוג מטבע",
        "ערך נקוב",
        "שער",
        "שווי שוק",
        "שעור מערך נקוב מונפק",
        "שעור מנכסי אפיק ההשקעה",
        "שעור מסך נכסי השקעה",
        "untitled1"
      ],
      "data": [
        [
          "הראלס ב תא100",
          1113232,
          "TASE",
          1523,
          "מניות",
          "שקל חדש",
          228226,
          1249.0,
          2850.54,
          0.11,
          11.74,
          0.96,
          ""
        ],
        [
          "פסגות סל ג תא100",
          1096593,
          "TASE",
          1108,
          "מניות",
          "שקל חדש",
          214312,
          1251.0,
          2681.04,
          0.15,
          11.04,
          0.91,
          ""
        ],
        [
          "'תכלית ת\"א100ת.סל א",
          1091818,
          "TASE",
          1223,
          "מניות",
          "שקל חדש",
          37952,
          12490.0,
          4740.2,
          0.09,
          19.53,
          1.6,
          ""
        ],
        [
          "DAXEX (DAXEX)",
          "DE0005933931",
          "אחר",
          98339,
          "מניות",
          "אירו",
          2346,
          8801.0,
          884.85,
          0.0,
          3.64,
          0.3,
          110691458
        ],
        [
          "ISHARES DJ (ITB",
          "US4642887529",
          "NYSE",
          98339,
          "מניות",
          "דולר אמריקאי",
          3852,
          2708.0,
          392.84,
          0.01,
          1.62,
          0.13,
          60133352
        ],
        [
          "ISHARES MDAX DE",
          "DE0005933923",
          "אחר",
          98339,
          "מניות",
          "אירו",
          592,
          17992.0,
          456.47,
          0.01,
          1.88,
          0.15,
          60318904
        ],
        [
          "ISHARES EUR 600 AUTO+PARTS",
          "DE000A0Q4R28",
          "אחר",
          98339,
          "מניות",
          "אירו",
          837,
          4827.0,
          173.15,
          0.04,
          0.71,
          0.06,
          60323334
        ],
        [
          "GUGGENHEIM(RYT)",
          "US78355W8174",
          "NYSE",
          98555,
          "מניות",
          "דולר אמריקאי",
          1375,
          9376.0,
          485.51,
          0.02,
          2.0,
          0.16,
          60150133
        ],
        [
          "HANG SE(2828 HK",
          "HK2828013055",
          "HKSE",
          97723,
          "מניות",
          "דולר הונג קונג",
          13237,
          9055.0,
          581.8,
          0.0,
          2.4,
          0.2,
          60160421
        ],
        [
          "(SXSEEX)יורו סטוק",
          "DE0005933956",
          "אחר",
          99307,
          "מניות",
          "אירו",
          3505,
          3016.0,
          453.03,
          0.0,
          1.87,
          0.15,
          110774866
        ],
        [
          "ISHARES STOXX EUROPE 600",
          "DE0002635307",
          "אחר",
          99341,
          "מניות",
          "אירו",
          2130,
          3380.0,
          308.54,
          0.0,
          1.27,
          0.1,
          60189891
        ],
        [
          "ISHARES M(EIRL)",
          "US46429B5075",
          "NYSE",
          99341,
          "מניות",
          "דולר אמריקאי",
          2174,
          4020.0,
          329.13,
          0.05,
          1.36,
          0.11,
          60257961
        ],
        [
          "LYXOR ETF CAC 40",
          "FR0007052782",
          "CAC",
          99964,
          "מניות",
          "אירו",
          1590,
          4337.5,
          295.56,
          0.0,
          1.22,
          0.1,
          60039740
        ],
        [
          "POWERSHARES QQQ TRUST SER",
          "US6311001043",
          "NASDAQ",
          99245,
          "מניות",
          "דולר אמריקאי",
          2312,
          10920.0,
          950.8,
          0.0,
          3.92,
          0.32,
          101122430
        ],
        [
          "CONSUMER DI(XLY",
          "US81369Y4070",
          "NYSE",
          99506,
          "מניות",
          "דולר אמריקאי",
          679,
          7910.0,
          202.27,
          0.0,
          0.83,
          0.07,
          60021169
        ],
        [
          "(SPY)אס.פי.די נסחר בדולר",
          "US78462F1030",
          "NYSE",
          99390,
          "מניות",
          "דולר אמריקאי",
          7656,
          20552.0,
          5925.65,
          0.0,
          24.41,
          2.01,
          110567872
        ],
        [
          "ENERGY SPDR(XLE",
          "US81369Y5069",
          "NYSE",
          99390,
          "מניות",
          "דולר אמריקאי",
          1181,
          6189.0,
          275.26,
          0.0,
          1.13,
          0.09,
          60024866
        ],
        [
          "VANGRD EMRG(VWO",
          "US9220428588",
          "NYSE",
          99237,
          "מניות",
          "דולר אמריקאי",
          3822,
          3458.0,
          497.73,
          0.0,
          2.05,
          0.17,
          60052768
        ],
        [
          "VANGUARD S&P 500 ETF",
          "US9229084135",
          "NYSE",
          99237,
          "מניות",
          "דולר אמריקאי",
          872,
          18856.0,
          619.22,
          0.0,
          2.55,
          0.21,
          60604105
        ],
        [
          "WISDOMTREE JAPAN HEDGED E",
          "US97717W8516",
          "NYSE",
          99939,
          "מניות",
          "דולר אמריקאי",
          7122,
          4371.0,
          1172.37,
          0.0,
          4.83,
          0.4,
          60147469
        ]
      ]
    },
    "אופציות": {
      "columns": [
        "שם המנפיק/שם נייר ערך",
        "מספר ני\"ע",
        "זירת מסחר",
        "ענף מסחר",
        "סוג מטבע",
        "ערך נקוב",
        "שער",
        "שווי שוק",
        "שעור מערך נקוב מונפק",
        "שעור מנכסי אפיק ההשקעה",
        "שעור מסך נכסי השקעה"
      ],
      "data": [
        [
          "דלר-6040.0385CM",
          81498826,
          "TASE",
          "מעוף",
          "שקל חדש",
          -450,
          4100,
          -18.45,
          0,
          -4.77,
          -0.01
        ],
        [
          "דלר-6040.0385PM",
          81498941,
          "TASE",
          "מעוף",
          "שקל חדש",
          450,
          90100,
          405.45,
          0,
          104.77,
          0.14
        ]
      ]
    },
    "מוצרים מובנים": {
      "columns": [
        "שם נייר ערך",
        "מספר ני\"ע",
        "נכס הבסיס",
        "דירוג",
        "שם מדרג",
        "תאריך רכישה",
        "מח\"מ",
        "סוג מטבע",
        "שיעור ריבית",
        "תשואה לפדיון",
        "ערך נקוב",
        "שער",
        "שווי שוק",
        "שעור מערך נקוב מונפק",
        "שעור מנכסי אפיק ההשקעה",
        "שעור מסך נכסי השקעה"
      ],
      "data": [
        [
          ".גלובל פיננס8אגח ד",
          1108620,
          "שכבת חוב",
          "A2",
          "מידרוג",
          "",
          1.48,
          "שקל חדש",
          10.13,
          3.5,
          256673.71,
          116.91,
          300.08,
          0.12,
          32.71,
          0.1
        ],
        [
          "גליל מור אגח א ז\"פ2015.12.30",
          1108877,
          "שכבת חוב",
          "Caa1",
          "מידרוג",
          "",
          1.18,
          "שקל חדש",
          7.69,
          18.44,
          626119.11,
          98.58,
          617.23,
          0.59,
          67.29,
          0.21
        ]
      ]
    },
    "לא סחיר - אג\"ח קונצרני": {
      "columns": [
        "שם המנפיק/שם נייר ערך",
        "מספר ני\"ע",
        "ספק המידע",
        "מספר מנפיק",
        "ענף מסחר",
        "דירוג",
        "שם מדרג",
        "תאריך רכישה",
        "מח\"מ",
        "סוג מטבע",
        "שיעור ריבית",
        "תשואה לפדיון",
        "ערך נקוב",
        "שער",
        "שווי הוגן",
        "שעור מערך נקוב מונפק",
        "שעור מנכסי אפיק ההשקעה",
        "שעור מסך נכסי השקעה",
        "untitled1"
      ],
      "data": [
        [
          "מקורות סד(נשר) 4.9% 2007/2036 6",
          1100908,
          "",
          1150,
          "שרותים",
          "AAA",
          "מעלות",
          "2007-01-04",
          10.34,
          "שקל חדש",
          4.9,
          1.41,
          30000.0,
          167.51,
          50.25,
          0.0,
          2.46,
          0.02,
          111009080
        ],
        [
          "סופר גז אג\"ח2025/2025 %5.4 (נשר",
          1106822,
          "",
          1486,
          "שרותים",
          "AA+",
          "מעלות",
          "2007-07-01",
          4.49,
          "שקל חדש",
          4.9,
          0.98,
          14622.95,
          141.89,
          20.75,
          0.0,
          1.02,
          0.01,
          111068227
        ],
        [
          "(נשר) 5.85% 13/2019 Y.די.בי.אס",
          1121490,
          "",
          2201,
          "שרותים",
          "AA",
          "מעלות",
          "2010-11-01",
          2.03,
          "שקל חדש",
          5.85,
          0.65,
          855500.05,
          118.3,
          1012.06,
          0.11,
          49.55,
          0.34,
          111214904
        ],
        [
          "2018/2025 7.15%דרך ארץ",
          100063205,
          "",
          99071,
          "שרותים",
          "A2",
          "מידרוג",
          "2011-08-07",
          5.9,
          "שקל חדש",
          7.15,
          1.58,
          102048.41,
          142.57,
          145.49,
          0.01,
          7.12,
          0.05,
          ""
        ],
        [
          ")בע\"מ1997)דרך ארץ הייווז",
          100062629,
          "",
          98673,
          "שרותים",
          "A2",
          "מידרוג",
          "2000-01-01",
          3.02,
          "שקל חדש",
          7.09,
          0.99,
          9820.8,
          142.74,
          14.02,
          0.0,
          0.69,
          0.0,
          ""
        ],
        [
          "דואר ישראל א2012/2021 4.13%",
          1119049,
          "",
          1541,
          "שרותים",
          "Baa1",
          "מידרוג",
          "2010-04-01",
          2.54,
          "שקל חדש",
          4.13,
          3.36,
          671982.58,
          113.44,
          762.3,
          0.3,
          37.32,
          0.26,
          111190492
        ],
        [
          "אלון חברת דלק(נשר)16/2023 5.35%",
          1101567,
          "",
          2202,
          "השקעה ואחזקות",
          "BBB-",
          "מעלות",
          "2007-02-01",
          3.35,
          "שקל חדש",
          5.6,
          5.95,
          31582.19,
          118.84,
          37.53,
          0.0,
          1.84,
          0.01,
          111015673
        ],
        [
          "אגרקסקו חב'ליצוא א(9.90% 08/2017",
          1109180,
          "",
          1507,
          "נדל\"ן ובינוי",
          "C",
          "מידרוג",
          "2007-12-27",
          1.03,
          "שקל חדש",
          9.9,
          53.78,
          24800.0,
          0.0,
          0.0,
          0.02,
          0.0,
          0.0,
          111091807
        ],
        [
          "אגרקסקו חב'ליצוא א2017/08 9.90%חש",
          1126770,
          "",
          1507,
          "נדל\"ן ובינוי",
          "C",
          "מידרוג",
          "2012-08-06",
          0.57,
          "שקל חדש",
          9.9,
          1.14,
          4960.0,
          0.0,
          0.0,
          0.0,
          0.0,
          0.0,
          111267704
        ],
        [
          "'אי.די.בי הסדר חוב אג\"ח סדרה ד",
          173601915,
          "",
          736,
          "השקעה ואחזקות",
          "ללא דירוג",
          "ללא דירוג",
          "2014-08-04",
          0.0,
          "שקל חדש",
          0.0,
          0.0,
          255393.0,
          0.0,
          0.0,
          0.0,
          0.0,
          0.0,
          ""
        ]
      ]
    },
    "לא סחיר - קרנות השקעה": {
      "columns": [
        "שם נייר ערך",
        "מספר ני\"ע",
        "סוג מטבע",
        "תאריך רכישה",
        "ערך נקוב",
        "שער",
        "שווי הוגן",
        "שעור מערך נקוב מונפק",
        "שעור מנכסי אפיק ההשקעה",
        "שעור מסך נכסי השקעה",
        "untitled1"
      ],
      "data": [
        [
          "PI FUND",
          "XSGGHHJHJ788",
          "דולר אמריקאי",
          "2015-11-26",
          230000,
          100.01,
          866.28,
          25.56,
          100,
          0.29,
          60397171
        ]
      ]
    },
    "לא סחיר - מוצרים מובנים": {
      "columns": [
        "שם המנפיק/שם נייר ערך",
        "מספר ני\"ע",
        "נכס הבסיס",
        "דירוג",
        "שם מדרג",
        "תאריך רכישה",
        "מח\"מ",
        "סוג מטבע",
        "שיעור ריבית",
        "תשואה לפדיון",
        "ערך נקוב",
        "שער",
        "שווי הוגן",
        "שעור מערך נקוב מונפק",
        "שעור מנכסי אפיק ההשקעה",
        "שעור מסך נכסי השקעה",
        "untitled1"
      ],
      "data": [
        [
          "2019 4.1%'גלובל פיננס ג'י.אר8ד",
          1116037,
          "שכבת חוב",
          "ללא דירוג",
          "ללא דירוג",
          "2000-01-01",
          0,
          "שקל חדש",
          4.1,
          4.1,
          83212.32,
          88.5,
          73.65,
          0.12,
          100,
          0.02,
          111160370
        ]
      ]
    },
    "הלוואות": {
      "columns": [
        "שם נייר ערך",
        "קונסורציום כן/לא",
        "מספר ני\"ע",
        "דירוג",
        "שם מדרג",
        "מח\"מ",
        "סוג מטבע",
        "שעור ריבית ממוצע",
        "תשואה לפדיון",
        "ערך נקוב",
        "שער",
        "שווי הוגן",
        "שעור מנכסי אפיק ההשקעה",
        "שעור מסך נכסי השקעה"
      ],
      "data": [
        [
          "הלוואה לעמיתים1",
          "לא",
          893000109,
          "AAA",
          "פנימי",
          1.61,
          "שקל חדש",
          0,
          1.4,
          14785656.14,
          99.81,
          14757.56,
          99.99,
          4.99
        ],
        [
          "חוזרים הלוואות",
          "לא",
          800069338,
          "AA+",
          "פנימי",
          0.0,
          "שקל חדש",
          0,
          0.0,
          798.6,
          100.0,
          0.8,
          0.0,
          0.0
        ]
      ]
    },
    "פקדונות מעל 3 חודשים": {
      "columns": [
        "שם נייר ערך",
        "מספר ני\"ע",
        "מספר מנפיק",
        "דירוג",
        "שם מדרג",
        "מח\"מ",
        "סוג מטבע",
        "תנאי ושעור ריבית",
        "תשואה לפדיון",
        "ערך נקוב",
        "שער",
        "שווי הוגן",
        "שעור מנכסי אפיק ההשקעה",
        "שעור מסך נכסי השקעה",
        "untitled1"
      ],
      "data": [
        [
          "פועלים פקדון2017/08 %70.5 (משכן)",
          "12 - 164774267",
          12,
          "AAA",
          "מעלות",
          0.71,
          "שקל חדש",
          5.7,
          0.18,
          98642.89,
          133.96,
          132.14,
          75.69,
          0.04,
          164774267
        ],
        [
          "פועלים פקדון2017/2008 %5.5 (משכן)",
          "12 - 164773350",
          12,
          "AAA",
          "מעלות",
          0.53,
          "שקל חדש",
          5.5,
          0.14,
          31117.52,
          136.37,
          42.43,
          24.31,
          0.01,
          164773350
        ]
      ]
    },
    "השקעות אחרות": {
      "columns": [
        "שם נייר ערך",
        "מספר הנייר",
        "דירוג",
        "שם המדרג",
        "שיעור הריבית",
        "סוג מטבע",
        "תשואה לפדיון",
        "שווי הוגן",
        "שעור מנכסי אפיק ההשקעה",
        "שעור מסך נכסי השקעה"
      ],
      "data": [
        [
          "חו\"ז דמי ניהול",
          "",
          "",
          "",
          0.0,
          "שקל חדש",
          0.0,
          -9.45,
          -16.66,
          0.0
        ],
        [
          "מס הכנסה חו\"ז",
          "",
          "",
          "",
          0.0,
          "שקל חדש",
          0.0,
          -0.67,
          -1.18,
          0.0
        ],
        [
          "עזריאלי אגח ב-ריבית לקבל",
          11344360,
          "AA+",
          "מעלות",
          0.65,
          "שקל חדש",
          1.03,
          3.69,
          6.51,
          0.0
        ],
        [
          "שלמה החז אגח טז-ריבית לקבל",
          14102810,
          "A",
          "מעלות",
          2.15,
          "שקל חדש",
          2.02,
          4.36,
          7.69,
          0.0
        ],
        [
          "POWERSHARES QQQ TRUST SER -דיבידנד לקבל",
          1011224300,
          "ללא דירוג",
          "ללא דירוג",
          0.0,
          "דולר אמריקאי",
          0.0,
          2.12,
          3.75,
          0.0
        ],
        [
          "(SPY)אס.פי.די נסחר בדולר-דיבידנד לקבל",
          1105678720,
          "ללא דירוג",
          "ללא דירוג",
          0.0,
          "דולר אמריקאי",
          0.0,
          23.24,
          40.98,
          0.01
        ]
      ]
    }
  }
}